.pylintrc
.readthedocs.yaml
.yamllint.yaml
ACKNOWLEDGEMENTS
AUTHORS
LICENSE
MANIFEST.in
README
acstore.ini
appveyor.yml
dependencies.ini
pyproject.toml
requirements.txt
run_tests.py
setup.cfg
setup.py
test_dependencies.ini
test_requirements.txt
tox.ini
.github/workflows/test_docker.yml
.github/workflows/test_docs.yml
.github/workflows/test_tox.yml
acstore/__init__.py
acstore/errors.py
acstore/fake_store.py
acstore/interface.py
acstore/profilers.py
acstore/sqlite_store.py
acstore.egg-info/PKG-INFO
acstore.egg-info/SOURCES.txt
acstore.egg-info/dependency_links.txt
acstore.egg-info/requires.txt
acstore.egg-info/top_level.txt
acstore/containers/__init__.py
acstore/containers/interface.py
acstore/containers/manager.py
acstore/helpers/__init__.py
acstore/helpers/json_serializer.py
acstore/helpers/schema.py
acstore/helpers/yaml_definitions_file.py
config/appveyor/install.ps1
config/appveyor/install.sh
config/appveyor/runtests.sh
config/dpkg/changelog
config/dpkg/clean
config/dpkg/compat
config/dpkg/control
config/dpkg/copyright
config/dpkg/rules
config/dpkg/source/format
docs/conf.py
docs/index.rst
docs/requirements.txt
docs/sources/api/acstore.containers.rst
docs/sources/api/acstore.helpers.rst
docs/sources/api/acstore.rst
docs/sources/api/modules.rst
docs/sources/user/Installation-instructions.md
docs/sources/user/index.rst
test_data/definitions.yaml
tests/__init__.py
tests/fake_store.py
tests/interface.py
tests/profilers.py
tests/sqlite_store.py
tests/test_lib.py
tests/containers/__init__.py
tests/containers/interface.py
tests/containers/manager.py
tests/helpers/__init__.py
tests/helpers/json_serializer.py
tests/helpers/schema.py
tests/helpers/yaml_definitions_file.py
utils/__init__.py
utils/check_dependencies.py
utils/dependencies.py
utils/update_release.sh