Metadata-Version: 2.1
Name: acstore
Version: 20240406
Summary: Attribute Container Storage (ACStore).
Home-page: https://github.com/log2timeline/acstore
Maintainer: Log2Timeline maintainers
Maintainer-email: log2timeline-maintainers@googlegroups.com
License: Apache License, Version 2.0
Classifier: Development Status :: 3 - Alpha
Classifier: Programming Language :: Python
Requires-Python: >=3.8
License-File: ACKNOWLEDGEMENTS
License-File: AUTHORS
License-File: LICENSE
License-File: README
Requires-Dist: PyYAML>=3.10
